{
  "contracts": {
    "RahatAccessManager": {
      "address": "0x59de52bc26218DE0aDd1B158459d83fa2F409855",
      "startBlock": 18501506
    },
    "RahatTreasury": {
      "address": "0x36da6C03d4a89982582230461BD6E586c1923d6b",
      "startBlock": 18501514
    },
    "RahatToken": {
      "address": "0x6A2Ac220060A277C1f37Cb1BC9b9259730280D8e",
      "startBlock": 18501518
    },
    "ERC2771Forwarder": {
      "address": "0xAAf06232582B43DAbE73Cc8aB7d97cf3D4289f31",
      "startBlock": 18501510
    }
  },
  "chainSettings": {
    "rpcUrl": "https://base-sepolia.g.alchemy.com/v2/QDCmOvFT118Of31RIv35kEn79gEi7_tH",
    "chainName": "Base sepolia",
    "nativeCurrency": {
      "name": "ETH",
      "symbol": "ETH"
    }
  }
}